eqnp/__init__.py
eqnp/expressions.py
eqnp/functions.py
eqnp/parser.py
eqnp-1.0.0.dist-info/LICENSE
eqnp-1.0.0.dist-info/METADATA
eqnp-1.0.0.dist-info/WHEEL
eqnp-1.0.0.dist-info/top_level.txt
eqnp-1.0.0.dist-info/RECORD
