Metadata-Version: 2.1
Name: eqnp
Version: 1.0.0
Summary: Symbolic calculus solver and mathematical simplification engine
Home-page: https://github.com/kdkasad/eqnp
Author: Kian Kasad
Author-email: dev@kasad.com
License: BSD-2-Clause-Patent
Platform: UNKNOWN
Requires-Python: >=3.6
License-File: LICENSE
